<?xml version="1.0" encoding="UTF-8" standalone="no"?><person><persona>
        <nombre>pedro jose</nombre>
        <apellidos>hernandez</apellidos>
        <salario>332608</salario>
        <edad>5</edad>
    </persona></person><?xml version="1.0" encoding="UTF-8" standalone="no"?><person><persona>
        <nombre>pedro jose</nombre>
        <apellidos>jaramillo</apellidos>
        <salario>3397514</salario>
        <edad>6</edad>
    </persona></person><?xml version="1.0" encoding="UTF-8" standalone="no"?><person><persona>
        <nombre>pedro jose</nombre>
        <apellidos>serrano</apellidos>
        <salario>1210829</salario>
        <edad>15</edad>
    </persona></person><?xml version="1.0" encoding="UTF-8" standalone="no"?><person><persona>
        <nombre>pedro joaquin</nombre>
        <apellidos>mesa</apellidos>
        <salario>5764020</salario>
        <edad>14</edad>
    </persona></person><?xml version="1.0" encoding="UTF-8" standalone="no"?><person><persona>
        <nombre>pedro carlos</nombre>
        <apellidos>lopez</apellidos>
        <salario>6270604</salario>
        <edad>13</edad>
    </persona></person><?xml version="1.0" encoding="UTF-8" standalone="no"?><person><persona>
        <nombre>pedro carlos</nombre>
        <apellidos>jaramillo</apellidos>
        <salario>1653020</salario>
        <edad>3</edad>
    </persona></person><?xml version="1.0" encoding="UTF-8" standalone="no"?><person><persona>
        <nombre>pedro mateo</nombre>
        <apellidos>gomez</apellidos>
        <salario>9527604</salario>
        <edad>7</edad>
    </persona></person><?xml version="1.0" encoding="UTF-8" standalone="no"?><person><persona>
        <nombre>pedro mateo</nombre>
        <apellidos>sanchez</apellidos>
        <salario>4390344</salario>
        <edad>17</edad>
    </persona></person><?xml version="1.0" encoding="UTF-8" standalone="no"?><person><persona>
        <nombre>pedro mateo</nombre>
        <apellidos>aponte</apellidos>
        <salario>5707206</salario>
        <edad>8</edad>
    </persona></person><?xml version="1.0" encoding="UTF-8" standalone="no"?><person><persona>
        <nombre>pedro mateo</nombre>
        <apellidos>jaramillo</apellidos>
        <salario>2115300</salario>
        <edad>9</edad>
    </persona></person><?xml version="1.0" encoding="UTF-8" standalone="no"?><person><persona>
        <nombre>pedro mateo</nombre>
        <apellidos>gutierrez</apellidos>
        <salario>7139599</salario>
        <edad>16</edad>
    </persona></person><?xml version="1.0" encoding="UTF-8" standalone="no"?><person><persona>
        <nombre>pedro santiago</nombre>
        <apellidos>gonzalez</apellidos>
        <salario>4753412</salario>
        <edad>4</edad>
    </persona></person><?xml version="1.0" encoding="UTF-8" standalone="no"?><person><persona>
        <nombre>pedro santiago</nombre>
        <apellidos>aponte</apellidos>
        <salario>7461690</salario>
        <edad>14</edad>
    </persona></person><?xml version="1.0" encoding="UTF-8" standalone="no"?><person><persona>
        <nombre>pedro santiago</nombre>
        <apellidos>ortiz</apellidos>
        <salario>1575071</salario>
        <edad>4</edad>
    </persona></person><?xml version="1.0" encoding="UTF-8" standalone="no"?><person><persona>
        <nombre>pedro santiago</nombre>
        <apellidos>gutierrez</apellidos>
        <salario>2971002</salario>
        <edad>12</edad>
    </persona></person><?xml version="1.0" encoding="UTF-8" standalone="no"?><person><persona>
        <nombre>pedro santiago</nombre>
        <apellidos>orozco</apellidos>
        <salario>7647418</salario>
        <edad>4</edad>
    </persona></person><?xml version="1.0" encoding="UTF-8" standalone="no"?><person><persona>
        <nombre>pedro felipe</nombre>
        <apellidos>martinez</apellidos>
        <salario>550667</salario>
        <edad>8</edad>
    </persona></person><?xml version="1.0" encoding="UTF-8" standalone="no"?><person><persona>
        <nombre>pedro felipe</nombre>
        <apellidos>sanchez</apellidos>
        <salario>6576344</salario>
        <edad>9</edad>
    </persona></person><?xml version="1.0" encoding="UTF-8" standalone="no"?><person><persona>
        <nombre>pedro felipe</nombre>
        <apellidos>aponte</apellidos>
        <salario>1034228</salario>
        <edad>10</edad>
    </persona></person><?xml version="1.0" encoding="UTF-8" standalone="no"?><person><persona>
        <nombre>pedro felipe</nombre>
        <apellidos>orozco</apellidos>
        <salario>6197843</salario>
        <edad>5</edad>
    </persona></person><?xml version="1.0" encoding="UTF-8" standalone="no"?><person><persona>
        <nombre>jose pedro</nombre>
        <apellidos>perez</apellidos>
        <salario>8548417</salario>
        <edad>17</edad>
    </persona></person><?xml version="1.0" encoding="UTF-8" standalone="no"?><person><persona>
        <nombre>jose pedro</nombre>
        <apellidos>lopez</apellidos>
        <salario>3388758</salario>
        <edad>7</edad>
    </persona></person><?xml version="1.0" encoding="UTF-8" standalone="no"?><person><persona>
        <nombre>jose pedro</nombre>
        <apellidos>mesa</apellidos>
        <salario>7676186</salario>
        <edad>6</edad>
    </persona></person><?xml version="1.0" encoding="UTF-8" standalone="no"?><person><persona>
        <nombre>jose joaquin</nombre>
        <apellidos>hernandez</apellidos>
        <salario>1880013</salario>
        <edad>2</edad>
    </persona></person><?xml version="1.0" encoding="UTF-8" standalone="no"?><person><persona>
        <nombre>jose joaquin</nombre>
        <apellidos>gonzalez</apellidos>
        <salario>7342491</salario>
        <edad>5</edad>
    </persona></person><?xml version="1.0" encoding="UTF-8" standalone="no"?><person><persona>
        <nombre>jose joaquin</nombre>
        <apellidos>orozco</apellidos>
        <salario>877469</salario>
        <edad>14</edad>
    </persona></person><?xml version="1.0" encoding="UTF-8" standalone="no"?><person><persona>
        <nombre>jose carlos</nombre>
        <apellidos>perez</apellidos>
        <salario>8540853</salario>
        <edad>11</edad>
    </persona></person><?xml version="1.0" encoding="UTF-8" standalone="no"?><person><persona>
        <nombre>jose carlos</nombre>
        <apellidos>garcia</apellidos>
        <salario>4221246</salario>
        <edad>7</edad>
    </persona></person><?xml version="1.0" encoding="UTF-8" standalone="no"?><person><persona>
        <nombre>jose carlos</nombre>
        <apellidos>ortiz</apellidos>
        <salario>7940601</salario>
        <edad>2</edad>
    </persona></person><?xml version="1.0" encoding="UTF-8" standalone="no"?><person><persona>
        <nombre>jose carlos</nombre>
        <apellidos>serrano</apellidos>
        <salario>7402807</salario>
        <edad>11</edad>
    </persona></person><?xml version="1.0" encoding="UTF-8" standalone="no"?><person><persona>
        <nombre>jose mateo</nombre>
        <apellidos>gonzalez</apellidos>
        <salario>5632674</salario>
        <edad>14</edad>
    </persona></person><?xml version="1.0" encoding="UTF-8" standalone="no"?><person><persona>
        <nombre>jose mateo</nombre>
        <apellidos>sanchez</apellidos>
        <salario>6689113</salario>
        <edad>15</edad>
    </persona></person><?xml version="1.0" encoding="UTF-8" standalone="no"?><person><persona>
        <nombre>jose mateo</nombre>
        <apellidos>mesa</apellidos>
        <salario>9757992</salario>
        <edad>2</edad>
    </persona></person><?xml version="1.0" encoding="UTF-8" standalone="no"?><person><persona>
        <nombre>jose santiago</nombre>
        <apellidos>perez</apellidos>
        <salario>5978338</salario>
        <edad>9</edad>
    </persona></person><?xml version="1.0" encoding="UTF-8" standalone="no"?><person><persona>
        <nombre>jose santiago</nombre>
        <apellidos>hernandez</apellidos>
        <salario>7595387</salario>
        <edad>3</edad>
    </persona></person><?xml version="1.0" encoding="UTF-8" standalone="no"?><person><persona>
        <nombre>jose santiago</nombre>
        <apellidos>orozco</apellidos>
        <salario>4006317</salario>
        <edad>11</edad>
    </persona></person><?xml version="1.0" encoding="UTF-8" standalone="no"?><person><persona>
        <nombre>jose sebastian</nombre>
        <apellidos>garcia</apellidos>
        <salario>4693262</salario>
        <edad>4</edad>
    </persona></person><?xml version="1.0" encoding="UTF-8" standalone="no"?><person><persona>
        <nombre>jose sebastian</nombre>
        <apellidos>mesa</apellidos>
        <salario>1932287</salario>
        <edad>13</edad>
    </persona></person><?xml version="1.0" encoding="UTF-8" standalone="no"?><person><persona>
        <nombre>jose felipe</nombre>
        <apellidos>lopez</apellidos>
        <salario>1858783</salario>
        <edad>8</edad>
    </persona></person><?xml version="1.0" encoding="UTF-8" standalone="no"?><person><persona>
        <nombre>jose felipe</nombre>
        <apellidos>gonzalez</apellidos>
        <salario>7075435</salario>
        <edad>15</edad>
    </persona></person><?xml version="1.0" encoding="UTF-8" standalone="no"?><person><persona>
        <nombre>jose felipe</nombre>
        <apellidos>gutierrez</apellidos>
        <salario>3060819</salario>
        <edad>4</edad>
    </persona></person><?xml version="1.0" encoding="UTF-8" standalone="no"?><person><persona>
        <nombre>joaquin pedro</nombre>
        <apellidos>lopez</apellidos>
        <salario>9803424</salario>
        <edad>5</edad>
    </persona></person><?xml version="1.0" encoding="UTF-8" standalone="no"?><person><persona>
        <nombre>joaquin pedro</nombre>
        <apellidos>ortiz</apellidos>
        <salario>1315815</salario>
        <edad>8</edad>
    </persona></person><?xml version="1.0" encoding="UTF-8" standalone="no"?><person><persona>
        <nombre>joaquin jose</nombre>
        <apellidos>garcia</apellidos>
        <salario>2933919</salario>
        <edad>14</edad>
    </persona></person><?xml version="1.0" encoding="UTF-8" standalone="no"?><person><persona>
        <nombre>joaquin jose</nombre>
        <apellidos>aponte</apellidos>
        <salario>1373327</salario>
        <edad>1</edad>
    </persona></person><?xml version="1.0" encoding="UTF-8" standalone="no"?><person><persona>
        <nombre>joaquin jose</nombre>
        <apellidos>mesa</apellidos>
        <salario>9393924</salario>
        <edad>13</edad>
    </persona></person><?xml version="1.0" encoding="UTF-8" standalone="no"?><person><persona>
        <nombre>joaquin jose</nombre>
        <apellidos>serrano</apellidos>
        <salario>2476650</salario>
        <edad>13</edad>
    </persona></person><?xml version="1.0" encoding="UTF-8" standalone="no"?><person><persona>
        <nombre>joaquin jose</nombre>
        <apellidos>gutierrez</apellidos>
        <salario>1598035</salario>
        <edad>4</edad>
    </persona></person><?xml version="1.0" encoding="UTF-8" standalone="no"?><person><persona>
        <nombre>joaquin carlos</nombre>
        <apellidos>aponte</apellidos>
        <salario>4776580</salario>
        <edad>3</edad>
    </persona></person><?xml version="1.0" encoding="UTF-8" standalone="no"?><person><persona>
        <nombre>joaquin carlos</nombre>
        <apellidos>jaramillo</apellidos>
        <salario>3061059</salario>
        <edad>12</edad>
    </persona></person><?xml version="1.0" encoding="UTF-8" standalone="no"?><person><persona>
        <nombre>joaquin mateo</nombre>
        <apellidos>hernandez</apellidos>
        <salario>142163</salario>
        <edad>11</edad>
    </persona></person><?xml version="1.0" encoding="UTF-8" standalone="no"?><person><persona>
        <nombre>joaquin mateo</nombre>
        <apellidos>sanchez</apellidos>
        <salario>8656356</salario>
        <edad>3</edad>
    </persona></person><?xml version="1.0" encoding="UTF-8" standalone="no"?><person><persona>
        <nombre>joaquin mateo</nombre>
        <apellidos>ortiz</apellidos>
        <salario>5807459</salario>
        <edad>11</edad>
    </persona></person><?xml version="1.0" encoding="UTF-8" standalone="no"?><person><persona>
        <nombre>joaquin santiago</nombre>
        <apellidos>garcia</apellidos>
        <salario>7890052</salario>
        <edad>14</edad>
    </persona></person><?xml version="1.0" encoding="UTF-8" standalone="no"?><person><persona>
        <nombre>joaquin santiago</nombre>
        <apellidos>gomez</apellidos>
        <salario>5251107</salario>
        <edad>9</edad>
    </persona></person><?xml version="1.0" encoding="UTF-8" standalone="no"?><person><persona>
        <nombre>joaquin santiago</nombre>
        <apellidos>serrano</apellidos>
        <salario>2023680</salario>
        <edad>14</edad>
    </persona></person><?xml version="1.0" encoding="UTF-8" standalone="no"?><person><persona>
        <nombre>joaquin felipe</nombre>
        <apellidos>gomez</apellidos>
        <salario>2735867</salario>
        <edad>8</edad>
    </persona></person><?xml version="1.0" encoding="UTF-8" standalone="no"?><person><persona>
        <nombre>joaquin felipe</nombre>
        <apellidos>aponte</apellidos>
        <salario>4993793</salario>
        <edad>10</edad>
    </persona></person><?xml version="1.0" encoding="UTF-8" standalone="no"?><person><persona>
        <nombre>joaquin felipe</nombre>
        <apellidos>jaramillo</apellidos>
        <salario>1696185</salario>
        <edad>13</edad>
    </persona></person><?xml version="1.0" encoding="UTF-8" standalone="no"?><person><persona>
        <nombre>carlos pedro</nombre>
        <apellidos>perez</apellidos>
        <salario>7591551</salario>
        <edad>3</edad>
    </persona></person><?xml version="1.0" encoding="UTF-8" standalone="no"?><person><persona>
        <nombre>carlos pedro</nombre>
        <apellidos>gonzalez</apellidos>
        <salario>7269670</salario>
        <edad>12</edad>
    </persona></person><?xml version="1.0" encoding="UTF-8" standalone="no"?><person><persona>
        <nombre>carlos pedro</nombre>
        <apellidos>aponte</apellidos>
        <salario>1800928</salario>
        <edad>10</edad>
    </persona></person><?xml version="1.0" encoding="UTF-8" standalone="no"?><person><persona>
        <nombre>carlos pedro</nombre>
        <apellidos>camargo</apellidos>
        <salario>7053226</salario>
        <edad>13</edad>
    </persona></person><?xml version="1.0" encoding="UTF-8" standalone="no"?><person><persona>
        <nombre>carlos pedro</nombre>
        <apellidos>serrano</apellidos>
        <salario>6230161</salario>
        <edad>11</edad>
    </persona></person><?xml version="1.0" encoding="UTF-8" standalone="no"?><person><persona>
        <nombre>carlos jose</nombre>
        <apellidos>martinez</apellidos>
        <salario>1798797</salario>
        <edad>13</edad>
    </persona></person><?xml version="1.0" encoding="UTF-8" standalone="no"?><person><persona>
        <nombre>carlos jose</nombre>
        <apellidos>sanchez</apellidos>
        <salario>5300953</salario>
        <edad>13</edad>
    </persona></person><?xml version="1.0" encoding="UTF-8" standalone="no"?><person><persona>
        <nombre>carlos jose</nombre>
        <apellidos>serrano</apellidos>
        <salario>5721261</salario>
        <edad>9</edad>
    </persona></person><?xml version="1.0" encoding="UTF-8" standalone="no"?><person><persona>
        <nombre>carlos joaquin</nombre>
        <apellidos>hernandez</apellidos>
        <salario>6585908</salario>
        <edad>4</edad>
    </persona></person><?xml version="1.0" encoding="UTF-8" standalone="no"?><person><persona>
        <nombre>carlos joaquin</nombre>
        <apellidos>gomez</apellidos>
        <salario>2543218</salario>
        <edad>12</edad>
    </persona></person><?xml version="1.0" encoding="UTF-8" standalone="no"?><person><persona>
        <nombre>carlos joaquin</nombre>
        <apellidos>sanchez</apellidos>
        <salario>4828511</salario>
        <edad>11</edad>
    </persona></person><?xml version="1.0" encoding="UTF-8" standalone="no"?><person><persona>
        <nombre>carlos mateo</nombre>
        <apellidos>jaramillo</apellidos>
        <salario>7365244</salario>
        <edad>5</edad>
    </persona></person><?xml version="1.0" encoding="UTF-8" standalone="no"?><person><persona>
        <nombre>carlos santiago</nombre>
        <apellidos>perez</apellidos>
        <salario>1183485</salario>
        <edad>13</edad>
    </persona></person><?xml version="1.0" encoding="UTF-8" standalone="no"?><person><persona>
        <nombre>carlos santiago</nombre>
        <apellidos>garcia</apellidos>
        <salario>4389414</salario>
        <edad>6</edad>
    </persona></person><?xml version="1.0" encoding="UTF-8" standalone="no"?><person><persona>
        <nombre>carlos santiago</nombre>
        <apellidos>gomez</apellidos>
        <salario>4720745</salario>
        <edad>12</edad>
    </persona></person><?xml version="1.0" encoding="UTF-8" standalone="no"?><person><persona>
        <nombre>carlos santiago</nombre>
        <apellidos>martinez</apellidos>
        <salario>3988577</salario>
        <edad>3</edad>
    </persona></person><?xml version="1.0" encoding="UTF-8" standalone="no"?><person><persona>
        <nombre>carlos santiago</nombre>
        <apellidos>mesa</apellidos>
        <salario>5715171</salario>
        <edad>1</edad>
    </persona></person><?xml version="1.0" encoding="UTF-8" standalone="no"?><person><persona>
        <nombre>carlos sebastian</nombre>
        <apellidos>perez</apellidos>
        <salario>6982267</salario>
        <edad>13</edad>
    </persona></person><?xml version="1.0" encoding="UTF-8" standalone="no"?><person><persona>
        <nombre>carlos sebastian</nombre>
        <apellidos>aponte</apellidos>
        <salario>3816775</salario>
        <edad>3</edad>
    </persona></person><?xml version="1.0" encoding="UTF-8" standalone="no"?><person><persona>
        <nombre>carlos felipe</nombre>
        <apellidos>gomez</apellidos>
        <salario>1784637</salario>
        <edad>14</edad>
    </persona></person><?xml version="1.0" encoding="UTF-8" standalone="no"?><person><persona>
        <nombre>carlos felipe</nombre>
        <apellidos>gonzalez</apellidos>
        <salario>8123954</salario>
        <edad>14</edad>
    </persona></person><?xml version="1.0" encoding="UTF-8" standalone="no"?><person><persona>
        <nombre>carlos felipe</nombre>
        <apellidos>sanchez</apellidos>
        <salario>2981267</salario>
        <edad>13</edad>
    </persona></person><?xml version="1.0" encoding="UTF-8" standalone="no"?><person><persona>
        <nombre>carlos felipe</nombre>
        <apellidos>camargo</apellidos>
        <salario>1582183</salario>
        <edad>7</edad>
    </persona></person><?xml version="1.0" encoding="UTF-8" standalone="no"?><person><persona>
        <nombre>mateo pedro</nombre>
        <apellidos>lopez</apellidos>
        <salario>8868544</salario>
        <edad>1</edad>
    </persona></person><?xml version="1.0" encoding="UTF-8" standalone="no"?><person><persona>
        <nombre>mateo pedro</nombre>
        <apellidos>jaramillo</apellidos>
        <salario>963378</salario>
        <edad>3</edad>
    </persona></person><?xml version="1.0" encoding="UTF-8" standalone="no"?><person><persona>
        <nombre>mateo jose</nombre>
        <apellidos>ortiz</apellidos>
        <salario>7431944</salario>
        <edad>10</edad>
    </persona></person><?xml version="1.0" encoding="UTF-8" standalone="no"?><person><persona>
        <nombre>mateo jose</nombre>
        <apellidos>orozco</apellidos>
        <salario>5067776</salario>
        <edad>1</edad>
    </persona></person><?xml version="1.0" encoding="UTF-8" standalone="no"?><person><persona>
        <nombre>mateo joaquin</nombre>
        <apellidos>sanchez</apellidos>
        <salario>510117</salario>
        <edad>13</edad>
    </persona></person><?xml version="1.0" encoding="UTF-8" standalone="no"?><person><persona>
        <nombre>mateo carlos</nombre>
        <apellidos>martinez</apellidos>
        <salario>5864972</salario>
        <edad>6</edad>
    </persona></person><?xml version="1.0" encoding="UTF-8" standalone="no"?><person><persona>
        <nombre>mateo carlos</nombre>
        <apellidos>aponte</apellidos>
        <salario>283156</salario>
        <edad>16</edad>
    </persona></person><?xml version="1.0" encoding="UTF-8" standalone="no"?><person><persona>
        <nombre>mateo carlos</nombre>
        <apellidos>mesa</apellidos>
        <salario>5312445</salario>
        <edad>3</edad>
    </persona></person><?xml version="1.0" encoding="UTF-8" standalone="no"?><person><persona>
        <nombre>mateo santiago</nombre>
        <apellidos>gonzalez</apellidos>
        <salario>2842165</salario>
        <edad>12</edad>
    </persona></person><?xml version="1.0" encoding="UTF-8" standalone="no"?><person><persona>
        <nombre>mateo santiago</nombre>
        <apellidos>gutierrez</apellidos>
        <salario>1377785</salario>
        <edad>12</edad>
    </persona></person><?xml version="1.0" encoding="UTF-8" standalone="no"?><person><persona>
        <nombre>mateo sebastian</nombre>
        <apellidos>garcia</apellidos>
        <salario>7437759</salario>
        <edad>8</edad>
    </persona></person><?xml version="1.0" encoding="UTF-8" standalone="no"?><person><persona>
        <nombre>mateo felipe</nombre>
        <apellidos>garcia</apellidos>
        <salario>6782840</salario>
        <edad>8</edad>
    </persona></person><?xml version="1.0" encoding="UTF-8" standalone="no"?><person><persona>
        <nombre>santiago pedro</nombre>
        <apellidos>hernandez</apellidos>
        <salario>1393026</salario>
        <edad>16</edad>
    </persona></person><?xml version="1.0" encoding="UTF-8" standalone="no"?><person><persona>
        <nombre>santiago pedro</nombre>
        <apellidos>mesa</apellidos>
        <salario>4754452</salario>
        <edad>2</edad>
    </persona></person><?xml version="1.0" encoding="UTF-8" standalone="no"?><person><persona>
        <nombre>santiago pedro</nombre>
        <apellidos>orozco</apellidos>
        <salario>7702724</salario>
        <edad>16</edad>
    </persona></person><?xml version="1.0" encoding="UTF-8" standalone="no"?><person><persona>
        <nombre>santiago jose</nombre>
        <apellidos>perez</apellidos>
        <salario>7732221</salario>
        <edad>16</edad>
    </persona></person><?xml version="1.0" encoding="UTF-8" standalone="no"?><person><persona>
        <nombre>santiago jose</nombre>
        <apellidos>lopez</apellidos>
        <salario>6047671</salario>
        <edad>11</edad>
    </persona></person><?xml version="1.0" encoding="UTF-8" standalone="no"?><person><persona>
        <nombre>santiago jose</nombre>
        <apellidos>martinez</apellidos>
        <salario>5465863</salario>
        <edad>9</edad>
    </persona></person><?xml version="1.0" encoding="UTF-8" standalone="no"?><person><persona>
        <nombre>santiago jose</nombre>
        <apellidos>sanchez</apellidos>
        <salario>3826518</salario>
        <edad>4</edad>
    </persona></person><?xml version="1.0" encoding="UTF-8" standalone="no"?><person><persona>
        <nombre>santiago jose</nombre>
        <apellidos>ortiz</apellidos>
        <salario>5583172</salario>
        <edad>4</edad>
    </persona></person><?xml version="1.0" encoding="UTF-8" standalone="no"?><person><persona>
        <nombre>santiago joaquin</nombre>
        <apellidos>aponte</apellidos>
        <salario>6306015</salario>
        <edad>16</edad>
    </persona></person><?xml version="1.0" encoding="UTF-8" standalone="no"?><person><persona>
        <nombre>santiago joaquin</nombre>
        <apellidos>ortiz</apellidos>
        <salario>1577158</salario>
        <edad>7</edad>
    </persona></person><?xml version="1.0" encoding="UTF-8" standalone="no"?><person><persona>
        <nombre>santiago joaquin</nombre>
        <apellidos>serrano</apellidos>
        <salario>5717175</salario>
        <edad>12</edad>
    </persona></person><?xml version="1.0" encoding="UTF-8" standalone="no"?><person><persona>
        <nombre>santiago carlos</nombre>
        <apellidos>garcia</apellidos>
        <salario>3806437</salario>
        <edad>14</edad>
    </persona></person><?xml version="1.0" encoding="UTF-8" standalone="no"?><person><persona>
        <nombre>santiago carlos</nombre>
        <apellidos>orozco</apellidos>
        <salario>3485397</salario>
        <edad>17</edad>
    </persona></person><?xml version="1.0" encoding="UTF-8" standalone="no"?><person><persona>
        <nombre>santiago mateo</nombre>
        <apellidos>hernandez</apellidos>
        <salario>9481932</salario>
        <edad>16</edad>
    </persona></person><?xml version="1.0" encoding="UTF-8" standalone="no"?><person><persona>
        <nombre>santiago mateo</nombre>
        <apellidos>gomez</apellidos>
        <salario>9328928</salario>
        <edad>1</edad>
    </persona></person><?xml version="1.0" encoding="UTF-8" standalone="no"?><person><persona>
        <nombre>santiago mateo</nombre>
        <apellidos>jaramillo</apellidos>
        <salario>9559693</salario>
        <edad>11</edad>
    </persona></person><?xml version="1.0" encoding="UTF-8" standalone="no"?><person><persona>
        <nombre>santiago sebastian</nombre>
        <apellidos>lopez</apellidos>
        <salario>2187897</salario>
        <edad>9</edad>
    </persona></person><?xml version="1.0" encoding="UTF-8" standalone="no"?><person><persona>
        <nombre>santiago sebastian</nombre>
        <apellidos>gomez</apellidos>
        <salario>8439282</salario>
        <edad>9</edad>
    </persona></person><?xml version="1.0" encoding="UTF-8" standalone="no"?><person><persona>
        <nombre>santiago sebastian</nombre>
        <apellidos>mesa</apellidos>
        <salario>9288109</salario>
        <edad>15</edad>
    </persona></person><?xml version="1.0" encoding="UTF-8" standalone="no"?><person><persona>
        <nombre>santiago sebastian</nombre>
        <apellidos>jaramillo</apellidos>
        <salario>8842388</salario>
        <edad>3</edad>
    </persona></person><?xml version="1.0" encoding="UTF-8" standalone="no"?><person><persona>
        <nombre>santiago sebastian</nombre>
        <apellidos>gutierrez</apellidos>
        <salario>1759257</salario>
        <edad>2</edad>
    </persona></person><?xml version="1.0" encoding="UTF-8" standalone="no"?><person><persona>
        <nombre>sebastian pedro</nombre>
        <apellidos>lopez</apellidos>
        <salario>1689285</salario>
        <edad>2</edad>
    </persona></person><?xml version="1.0" encoding="UTF-8" standalone="no"?><person><persona>
        <nombre>sebastian pedro</nombre>
        <apellidos>hernandez</apellidos>
        <salario>2271967</salario>
        <edad>14</edad>
    </persona></person><?xml version="1.0" encoding="UTF-8" standalone="no"?><person><persona>
        <nombre>sebastian pedro</nombre>
        <apellidos>martinez</apellidos>
        <salario>1074272</salario>
        <edad>10</edad>
    </persona></person><?xml version="1.0" encoding="UTF-8" standalone="no"?><person><persona>
        <nombre>sebastian pedro</nombre>
        <apellidos>jaramillo</apellidos>
        <salario>8747697</salario>
        <edad>13</edad>
    </persona></person><?xml version="1.0" encoding="UTF-8" standalone="no"?><person><persona>
        <nombre>sebastian pedro</nombre>
        <apellidos>gutierrez</apellidos>
        <salario>8135750</salario>
        <edad>8</edad>
    </persona></person><?xml version="1.0" encoding="UTF-8" standalone="no"?><person><persona>
        <nombre>sebastian jose</nombre>
        <apellidos>martinez</apellidos>
        <salario>2914605</salario>
        <edad>13</edad>
    </persona></person><?xml version="1.0" encoding="UTF-8" standalone="no"?><person><persona>
        <nombre>sebastian joaquin</nombre>
        <apellidos>perez</apellidos>
        <salario>3356612</salario>
        <edad>13</edad>
    </persona></person><?xml version="1.0" encoding="UTF-8" standalone="no"?><person><persona>
        <nombre>sebastian joaquin</nombre>
        <apellidos>lopez</apellidos>
        <salario>8230329</salario>
        <edad>7</edad>
    </persona></person><?xml version="1.0" encoding="UTF-8" standalone="no"?><person><persona>
        <nombre>sebastian joaquin</nombre>
        <apellidos>serrano</apellidos>
        <salario>4991099</salario>
        <edad>10</edad>
    </persona></person><?xml version="1.0" encoding="UTF-8" standalone="no"?><person><persona>
        <nombre>sebastian carlos</nombre>
        <apellidos>lopez</apellidos>
        <salario>7437425</salario>
        <edad>2</edad>
    </persona></person><?xml version="1.0" encoding="UTF-8" standalone="no"?><person><persona>
        <nombre>sebastian carlos</nombre>
        <apellidos>aponte</apellidos>
        <salario>1065307</salario>
        <edad>12</edad>
    </persona></person><?xml version="1.0" encoding="UTF-8" standalone="no"?><person><persona>
        <nombre>sebastian carlos</nombre>
        <apellidos>jaramillo</apellidos>
        <salario>1305977</salario>
        <edad>4</edad>
    </persona></person><?xml version="1.0" encoding="UTF-8" standalone="no"?><person><persona>
        <nombre>sebastian mateo</nombre>
        <apellidos>ortiz</apellidos>
        <salario>6892700</salario>
        <edad>10</edad>
    </persona></person><?xml version="1.0" encoding="UTF-8" standalone="no"?><person><persona>
        <nombre>sebastian santiago</nombre>
        <apellidos>perez</apellidos>
        <salario>5849066</salario>
        <edad>11</edad>
    </persona></person><?xml version="1.0" encoding="UTF-8" standalone="no"?><person><persona>
        <nombre>sebastian santiago</nombre>
        <apellidos>gutierrez</apellidos>
        <salario>8641424</salario>
        <edad>7</edad>
    </persona></person><?xml version="1.0" encoding="UTF-8" standalone="no"?><person><persona>
        <nombre>sebastian felipe</nombre>
        <apellidos>orozco</apellidos>
        <salario>1850483</salario>
        <edad>13</edad>
    </persona></person><?xml version="1.0" encoding="UTF-8" standalone="no"?><person><persona>
        <nombre>felipe pedro</nombre>
        <apellidos>lopez</apellidos>
        <salario>4096315</salario>
        <edad>8</edad>
    </persona></person><?xml version="1.0" encoding="UTF-8" standalone="no"?><person><persona>
        <nombre>felipe pedro</nombre>
        <apellidos>hernandez</apellidos>
        <salario>7858874</salario>
        <edad>16</edad>
    </persona></person><?xml version="1.0" encoding="UTF-8" standalone="no"?><person><persona>
        <nombre>felipe pedro</nombre>
        <apellidos>gonzalez</apellidos>
        <salario>7797786</salario>
        <edad>2</edad>
    </persona></person>